pynics/__init__.py
pynics/__main__.py
pynics/nics.py
pynics/nicsanalyse.py
pynics/splitcell.py
pynics/utils.py
pynics/binparse/__init__.py
pynics/binparse/castep_bin_cell.py
pynics/binparse/castep_bin_params.py
pynics/binparse/castep_bin_results.py
pynics/binparse/castepfile.py
pynics/binparse/currentfile.py
pynics/binparse/forbinfile.py
pynics/freeform/__init__.py
pynics/freeform/io_freeform.py
pynics/freeform/nicsfile.py
pynics/freeform/units.py
pynics-0.1.1.dist-info/LICENSE
pynics-0.1.1.dist-info/METADATA
pynics-0.1.1.dist-info/WHEEL
pynics-0.1.1.dist-info/entry_points.txt
pynics-0.1.1.dist-info/top_level.txt
pynics-0.1.1.dist-info/RECORD
